symlik/__init__.py
symlik/calculus.py
symlik/contribution.py
symlik/contributions.py
symlik/distributions.py
symlik/evaluate.py
symlik/fitted.py
symlik/mixture.py
symlik/model.py
symlik/regression.py
symlik/series.py
symlik/utils.py
symlik/rules/__init__.py
symlik-0.4.0.dist-info/METADATA
symlik-0.4.0.dist-info/WHEEL
symlik-0.4.0.dist-info/top_level.txt
symlik-0.4.0.dist-info/RECORD
